sl_pos2_api/__init__.py
sl_pos2_api/admin_auth.py
sl_pos2_api/app_auth.py
sl_pos2_api/common.py
sl_pos2_api/order_api.py
sl_pos2_api/utils/__init__.py
sl_pos2_api-0.2.9.dist-info/licenses/LICENSE
sl_pos2_api-0.2.9.dist-info/METADATA
sl_pos2_api-0.2.9.dist-info/WHEEL
sl_pos2_api-0.2.9.dist-info/top_level.txt
sl_pos2_api-0.2.9.dist-info/RECORD
